pppps2pc/__init__.py
pppps2pc/__main__.py
pppps2pc/constants.py
pppps2pc/main.py
pppps2pc/py.typed
pppps2pc/utils.py
pppps2pc-0.1.2.dist-info/METADATA
pppps2pc-0.1.2.dist-info/WHEEL
pppps2pc-0.1.2.dist-info/entry_points.txt
pppps2pc-0.1.2.dist-info/licenses/LICENSE.txt
pppps2pc-0.1.2.dist-info/RECORD
