Metadata-Version: 2.4
Name: pppps2pc
Version: 0.1.2
Summary: Extremely simple tool to enable the ParaParaParadise PS2 controller on a PC.
License-Expression: MIT
License-File: LICENSE.txt
Keywords: controller,para para paradise,peripherals,ps2,udev,usb,utilities
Author: Andrew Udvare
Author-email: audvare@gmail.com
Requires-Python: >=3.10,<4.0
Classifier: Development Status :: 4 - Beta
Classifier: Intended Audience :: Developers
Classifier: Programming Language :: Python
Classifier: Programming Language :: Python :: 3.10
Classifier: Programming Language :: Python :: 3.11
Classifier: Programming Language :: Python :: 3.12
Classifier: Programming Language :: Python :: 3.13
Classifier: Programming Language :: Python :: 3.14
Classifier: Typing :: Typed
Requires-Dist: bascom (>=0.1.0,<0.2.0)
Requires-Dist: click (>=8.3.1,<9.0.0)
Requires-Dist: hidapi (>=0.15.0,<0.16.0)
Requires-Dist: typing-extensions (>=4.15.0,<5.0.0)
Project-URL: Documentation, https://pppps2pc.readthedocs.org
Project-URL: Homepage, https://tatsh.github.io/pppps2pc/
Project-URL: Issues, https://github.com/Tatsh/pppps2pc/issues
Project-URL: Repository, https://github.com/Tatsh/pppps2pc
